pyregexkit/__init__.py
pyregexkit/core.py
pyregexkit-0.1.0.dist-info/METADATA
pyregexkit-0.1.0.dist-info/WHEEL
pyregexkit-0.1.0.dist-info/top_level.txt
pyregexkit-0.1.0.dist-info/RECORD
