Metadata-Version: 2.4
Name: pyregexkit
Version: 0.1.0
Summary: Simplify regex matching, extraction, and replacement with human-friendly syntax
Author: PyLib Contributors
License: MIT
Keywords: regex,pattern,matching,extraction
Classifier: Development Status :: 3 - Alpha
Classifier: Intended Audience :: Developers
Classifier: License :: OSI Approved :: MIT License
Classifier: Programming Language :: Python :: 3
Requires-Python: >=3.8
